omnitrack/__init__.py
omnitrack/core/api.py
omnitrack/core/batching.py
omnitrack/core/config_utils.py
omnitrack/core/context.py
omnitrack/core/interfaces.py
omnitrack/core/router.py
omnitrack/core/session.py
omnitrack/core/types.py
omnitrack/sinks/__init__.py
omnitrack/sinks/console.py
omnitrack/sinks/jsonl.py
omnitrack/sinks/wandb.py
omnitrack/utils/__init__.py
omnitrack/utils/decorators.py
omnitrack/utils/helpers.py
omnitrack-0.1.0.dist-info/METADATA
omnitrack-0.1.0.dist-info/WHEEL
omnitrack-0.1.0.dist-info/licenses/LICENSE
omnitrack-0.1.0.dist-info/RECORD
