Metadata-Version: 2.4
Name: omnitrack
Version: 0.1.0
Summary: Unified logging and experiment tracking for research workflows
Project-URL: Homepage, https://github.com/lars-quaedvlieg/omnitrack
Project-URL: Issues, https://github.com/lars-quaedvlieg/omnitrack/issues
Author-email: Lars Quaedvlieg <larsquaedvlieg@outlook.com>
License: MIT
License-File: LICENSE
Requires-Python: >=3.10
Requires-Dist: hydra-core>=1.3.2
Requires-Dist: numpy<2
Requires-Dist: psutil>=7.1.0
Requires-Dist: rich>=14.1.0
Requires-Dist: torch>=2.8.0
Requires-Dist: wandb>=0.22.0
Provides-Extra: dev
Requires-Dist: black; extra == 'dev'
Requires-Dist: build; extra == 'dev'
Requires-Dist: pytest; extra == 'dev'
Requires-Dist: ruff; extra == 'dev'
Requires-Dist: twine; extra == 'dev'
